preemptive_debugger/__init__.py
preemptive_debugger/preemptive_debugger.py
preemptive_debugger-0.0.1.dist-info/LICENSE
preemptive_debugger-0.0.1.dist-info/METADATA
preemptive_debugger-0.0.1.dist-info/WHEEL
preemptive_debugger-0.0.1.dist-info/top_level.txt
preemptive_debugger-0.0.1.dist-info/RECORD
