Metadata-Version: 2.1
Name: preemptive_debugger
Version: 0.0.1
Summary: A simple method to interactively preempt a running script to run a debugger
Home-page: https://github.com/tylerlum/preemptive_debugger
Author: Tyler Lum
Author-email: tylergwlum@gmail.com
License: UNKNOWN
Keywords: python,debugger,preemptive,interactive
Platform: UNKNOWN
Classifier: Intended Audience :: Developers
Classifier: Programming Language :: Python :: 3
License-File: LICENSE
